kgc_chart/__init__.py
kgc_chart/krueger_class.py
libname/__init__.py
libname/krueger_class.py
kgc_chart-1.1.0.dist-info/METADATA
kgc_chart-1.1.0.dist-info/WHEEL
kgc_chart-1.1.0.dist-info/top_level.txt
kgc_chart-1.1.0.dist-info/RECORD
