Metadata-Version: 2.1
Name: kgc-chart
Version: 1.1.0
Summary: Generating Krüger-Gauge-Circular-Charts
Home-page: UNKNOWN
Author: Christoph Krüger
Author-email: <christoph.kruger@yahoo.com>
License: UNKNOWN
Keywords: python,gauge chart,circular gauge chart,charts
Platform: UNKNOWN
Classifier: Development Status :: 4 - Beta
Classifier: Intended Audience :: Developers
Classifier: Programming Language :: Python :: 3
Classifier: Operating System :: Unix
Classifier: Operating System :: MacOS :: MacOS X
Classifier: Operating System :: Microsoft :: Windows
Requires-Dist: python-math
Requires-Dist: pycairo
Requires-Dist: pillow
Requires-Dist: matplotlib
